{"edges": [{"weight": "3606", "target": "Netanya, Israel", "source": "Rehovot, Israel"}, {"weight": "3011", "target": "Haifa, Israel", "source": "Netanya, Israel"}, {"weight": "2112", "target": "Rehovot, Israel", "source": "Ashdod, Israel"}, {"weight": "3008", "target": "Netanya, Israel", "source": "Haifa, Israel"}, {"weight": "1896", "target": "Ashdod, Israel", "source": "Rehovot, Israel"}, {"weight": "5494", "target": "Rehovot, Israel", "source": "Haifa, Israel"}, {"weight": "5379", "target": "Haifa, Israel", "source": "Rehovot, Israel"}, {"weight": "5536", "target": "Ashdod, Israel", "source": "Haifa, Israel"}, {"weight": "3700", "target": "Rehovot, Israel", "source": "Netanya, Israel"}, {"weight": "3438", "target": "Ashdod, Israel", "source": "Netanya, Israel"}, {"weight": "5995", "target": "Haifa, Israel", "source": "Ashdod, Israel"}, {"weight": "3603", "target": "Netanya, Israel", "source": "Ashdod, Israel"}], "driversAmount": "1", "verticals": [{"name": "Rehovot, Israel"}, {"name": "Ashdod, Israel"}, {"name": "Haifa, Israel"}, {"name": "Netanya, Israel"}]}